{
  "country": "france",
  "key": "hbo",
  "list": "movie",
  "date": "202607211706",
  "entries": [
    {
      "rank": 1,
      "id": "tt1464335",
      "name": "Uncharted",
      "tmdbPosterUrl": "https://image.tmdb.org/t/p/w780/iNV2wiYpSBXJuFeEZUHC92zgcdl.jpg",
      "rating": 6.886,
      "year": 2022,
      "days": 3,
      "trend": {
        "dir": "same",
        "delta": 0
      }
    },
    {
      "rank": 2,
      "id": "tt0332452",
      "name": "Troie",
      "tmdbPosterUrl": "https://image.tmdb.org/t/p/w780/pkKBYrihVm5kuBgOH04KagSids0.jpg",
      "rating": 7.177,
      "year": 2004,
      "days": 17,
      "trend": {
        "dir": "same",
        "delta": 0
      }
    },
    {
      "rank": 3,
      "id": "tt1517268",
      "name": "Barbie",
      "tmdbPosterUrl": "https://image.tmdb.org/t/p/w780/iuFNMS8U5cb6xfzi51Dbkovj7vM.jpg",
      "rating": 6.917,
      "year": 2023,
      "days": 45,
      "trend": {
        "dir": "new",
        "delta": null
      }
    },
    {
      "rank": 4,
      "id": "tt27534307",
      "name": "Speak No Evil",
      "tmdbPosterUrl": "https://image.tmdb.org/t/p/w780/ueffCcq485jkEQMY30yCDmGEksQ.jpg",
      "rating": 7.118,
      "year": 2024,
      "days": null,
      "trend": {
        "dir": "new",
        "delta": null
      }
    },
    {
      "rank": 5,
      "id": "tt12593682",
      "name": "Bullet Train",
      "tmdbPosterUrl": "https://image.tmdb.org/t/p/w780/uJvMXO1DNEER2lZocNjJy2zXtYs.jpg",
      "rating": 7.413,
      "year": 2022,
      "days": 10,
      "trend": {
        "dir": "down",
        "delta": 2
      }
    },
    {
      "rank": 6,
      "id": "tt2094766",
      "name": "Assassin's Creed",
      "tmdbPosterUrl": "https://image.tmdb.org/t/p/w780/nDkC47MBBjRyk3damnqMgQGlwIe.jpg",
      "rating": 5.438,
      "year": 2016,
      "days": 26,
      "trend": {
        "dir": "new",
        "delta": null
      }
    },
    {
      "rank": 7,
      "id": "tt1020558",
      "name": "Centurion",
      "tmdbPosterUrl": "https://image.tmdb.org/t/p/w780/QTqUs4JUdI6MI9lNXHjqnaiav4.jpg",
      "rating": 6.238,
      "year": 2010,
      "days": 23,
      "trend": {
        "dir": "down",
        "delta": 3
      }
    },
    {
      "rank": 8,
      "id": "tt0118883",
      "name": "Complots",
      "tmdbPosterUrl": "https://image.tmdb.org/t/p/w780/pPgI07FKnGKuhLm667rO3Oa04BX.jpg",
      "rating": 6.628,
      "year": 1997,
      "days": 1,
      "trend": {
        "dir": "down",
        "delta": 3
      }
    },
    {
      "rank": 9,
      "id": "tt1282140",
      "name": "Easy Girl",
      "tmdbPosterUrl": "https://image.tmdb.org/t/p/w780/nLdSvAisVDItlHHg1u667iaHZTj.jpg",
      "rating": 6.805,
      "year": 2010,
      "days": 8,
      "trend": {
        "dir": "down",
        "delta": 3
      }
    },
    {
      "rank": 10,
      "id": "tt8368406",
      "name": "Vivarium",
      "tmdbPosterUrl": "https://image.tmdb.org/t/p/w780/2SAH6napkUWibaAJ4oXr8dAVTIm.jpg",
      "rating": 6.062,
      "year": 2019,
      "days": 30,
      "trend": {
        "dir": "down",
        "delta": 3
      }
    }
  ]
}
